Workbook

Sheet Backlog
A1: Use Case | B1: User Story | C1: Acteur | D1: Tâche principale | E1: Description | F1: Estim. UI / Frontend (j/h) | G1: Estim. Backend / Logique (j/h) | H1: Total (j/h)
A2: ━━━ SECTION A — FRONTEND (React 18 · TypeScript · Vite · Tailwind CSS) ━━━
A3: Module FE-0 — Setup & Infrastructure Frontend
A4: UC-FE-SETUP | B4: Init Vite + React + TypeScript + ESLint + Prettier (path aliases, tsconfig strict) | C4: Développeur | D4: Config projet | E4: Scaffolding vite@7, @vitejs/plugin-react, typescript-eslint 9, path aliases @/ → src/, .env.local VITE_API_URL | F4: 0.25 | G4: 0.25 | H4: =F4+G4 -> 0.5
A5: UC-FE-SETUP | B5: Thème Tailwind CSS personnalisé + composants atomiques (Button, Card, Input, MadarailLogo) | C5: Développeur | D5: Design system | E5: Palette madarail (navy #0A2341, red #E30613, rail #F4F8FB), variantes Button primary/secondary, Card + titre, Input + label, SVG logo inline | F5: 0.5 | G5: 0 | H5: =F5+G5 -> 0.5
A6: UC-FE-SETUP | B6: Architecture AppContext (Context API, currentUser en mémoire, currentView, isOnline) | C6: Développeur | D6: État global | E6: useAppContext hook, état : currentUser (mémoire — jamais localStorage), currentView + guards, isOnline via window.addEventListener online/offline | F6: 0 | G6: 0.5 | H6: =F6+G6 -> 0.5
A7: UC-FE-SETUP | B7: Config PWA : vite-plugin-pwa, manifest.json, Service Worker Workbox, mode standalone | C7: Développeur | D7: PWA | E7: manifest thème madarail navy, icônes 192/512px, stratégie Network-First API, Cache-First assets statiques, installable Android/iOS | F7: 0 | G7: 0.5 | H7: =F7+G7 -> 0.5
A8: Sous-total Module FE-0 — Setup & Infrastructure Frontend | F8: =SUM(F4:F7) -> 0.75 | G8: =SUM(G4:G7) -> 1.25 | H8: =SUM(H4:H7) -> 2
A9: Module FE-1 — Authentification (UI + gestion tokens JWT)
A10: UC-FE-AUTH | B10: Page connexion (email/mot de passe, logo Madarail, messages d'erreur traduits) | C10: Agent / Admin | D10: Formulaire login | E10: Champs email + mdp, logo SVG MadarailLogo centré, gestion erreurs API (401 invalid credentials), états loading | F10: 0.25 | G10: 0.25 | H10: =F10+G10 -> 0.5
A11: UC-FE-AUTH | B11: Gestion tokens JWT : accessToken en mémoire + intercepteur Axios refresh (401 → POST /auth/refresh → retry) | C11: Agent / Admin | D11: JWT client | E11: Instance axios avec Authorization: Bearer, intercepteur response : 401 → appel /auth/refresh (cookie httpOnly envoyé auto) → mise à jour accessToken → retry requête originale | F11: 0 | G11: 0.75 | H11: =F11+G11 -> 0.75
A12: UC-FE-AUTH | B12: Guards frontend + redirections post-login par rôle (admin→dashboard, agent→pos, contrôleur→sales) | C12: Agent / Admin | D12: Guards & routing | E12: currentView initialisé selon role à la connexion, guards bloquant accès non autorisé, redirect vers vue de fallback définie par rôle | F12: 0 | G12: 0.25 | H12: =F12+G12 -> 0.25
A13: UC-FE-AUTH | B13: Logout : POST /auth/logout (révocation refresh token) + nettoyage état React | C13: Agent / Admin | D13: Déconnexion | E13: Appel POST /auth/logout, mise à null de currentUser et accessToken, retour à l'écran de connexion | F13: 0 | G13: 0.25 | H13: =F13+G13 -> 0.25
A14: Sous-total Module FE-1 — Authentification | F14: =SUM(F10:F13) -> 0.25 | G14: =SUM(G10:G13) -> 1.5 | H14: =SUM(H10:H13) -> 1.75
A15: Module FE-2 — Layout & Navigation
A16: UC-FE-NAV | B16: Sidebar responsive : desktop fixe rétractable (localStorage), mobile tiroir overlay + animation | C16: Tous | D16: Sidebar | E16: lg:fixed, overlay mobile fond semi-transparent, animation translate-x, état collapsed persisté "madarail-sidebar-collapsed", logo + badge version | F16: 0.75 | G16: 0.25 | H16: =F16+G16 -> 1
A17: UC-FE-NAV | B17: Menu filtré par rôle (7 items admin / 5 agent / 3 contrôleur) + surlignage item actif | C17: Tous | D17: Menu par rôle | E17: menuItems[] avec propriété roles[], filtre visibleItems, highlight currentView, icônes Lucide React | F17: 0 | G17: 0.25 | H17: =F17+G17 -> 0.25
A18: UC-FE-NAV | B18: Header mobile (hamburger, titre vue courante, badge OfflineIndicator compact) | C18: Tous | D18: Header mobile | E18: Barre top fixe < 1024px, icône WifiOff amber si !isOnline, titre dynamique par currentView | F18: 0.25 | G18: 0 | H18: =F18+G18 -> 0.25
A19: Sous-total Module FE-2 — Layout & Navigation | F19: =SUM(F16:F18) -> 1 | G19: =SUM(G16:G18) -> 0.5 | H19: =SUM(H16:H18) -> 1.5
A20: Module FE-3 — Couche API client (Axios + hooks + SSE)
A21: UC-FE-API | B21: Instance Axios : baseURL VITE_API_URL, headers Authorization Bearer, gestion erreurs normalisée | C21: Développeur | D21: Config Axios | E21: Singleton axios avec baseURL, intercepteur request → inject Bearer token, intercepteur response → gestion 401 (refresh) et 403 (alert rôle) | F21: 0 | G21: 0.25 | H21: =F21+G21 -> 0.25
A22: UC-FE-API | B22: Fonctions API par entité (auth, routes, sales, reservations, users) avec types TypeScript | C22: Développeur | D22: Services API | E22: Modules api/*.ts : fonctions typées (getRoutes, createSale, createReservation, etc.), DTOs request/response alignés avec le backend NestJS | F22: 0 | G22: 0.5 | H22: =F22+G22 -> 0.5
A23: UC-FE-API | B23: Hooks data-fetching personnalisés (useRoutes, useSales, useReservations) avec état loading/error | C23: Développeur | D23: Hooks React | E23: Hooks useEffect + useState ou TanStack Query léger, cache local, refetch on focus, invalidation après mutation (vente, réservation) | F23: 0 | G23: 0.5 | H23: =F23+G23 -> 0.5
A24: UC-FE-API | B24: Hook useSSE : consommation EventSource GET /events/routes, mise à jour stock catalogue en temps réel | C24: Développeur | D24: Hook SSE | E24: new EventSource("/events/routes", {withCredentials:true}), parse événement route-updated {id, seatsAvailable}, màj catalogue sans reload, cleanup sur démontage | F24: 0 | G24: 0.5 | H24: =F24+G24 -> 0.5
A25: Sous-total Module FE-3 — Couche API client | F25: =SUM(F21:F24) -> 0 | G25: =SUM(G21:G24) -> 1.75 | H25: =SUM(H21:H24) -> 1.75
A26: Module FE-4 — Tableau de bord (admin uniquement)
A27: UC-FE-DASH | B27: KPI widgets temps réel : recettes du jour, billets vendus, transactions, panier moyen, trajets actifs | C27: Admin | D27: KPIs temps réel | E27: 5 cards avec icônes Lucide, calcul depuis GET /sales?date=today, formatAriary(), mise à jour à chaque invalidation du cache | F27: 0.5 | G27: 0.5 | H27: =F27+G27 -> 1
A28: UC-FE-DASH | B28: Top 5 trajets les plus vendus (classés par revenus décroissants — départ→arrivée, classe, qté, montant) | C28: Admin | D28: Top 5 trajets | E28: Agrégation côté frontend sur sales du jour, tri revenue DESC, tableau 5 lignes avec badge classe et formatAriary | F28: 0.25 | G28: 0.25 | H28: =F28+G28 -> 0.5
A29: UC-FE-DASH | B29: Répartition opérateurs Mobile Money (barres MVola / Orange Money / Airtel Money — nb + %) | C29: Admin | D29: Barres Mobile Money | E29: Comptage par paymentMethod, barres CSS width proportionnelle, affichage nb transactions + pourcentage | F29: 0.25 | G29: 0.25 | H29: =F29+G29 -> 0.5
A30: UC-FE-DASH | B30: Histogramme ventes par heure (revenus cumulés par tranche horaire, 0h–23h) | C30: Admin | D30: Histogramme horaire | E30: Regroupement par heure(createdAt), tableau 24 slots, barres SVG ou div height proportionnelle au revenu max de la journée | F30: 0.25 | G30: 0.25 | H30: =F30+G30 -> 0.5
A31: Sous-total Module FE-4 — Tableau de bord | F31: =SUM(F27:F30) -> 1.25 | G31: =SUM(G27:G30) -> 1.25 | H31: =SUM(H27:H30) -> 2.5
A32: Module FE-5 — POS — Vente de billets (cœur applicatif)
A33: UC-FE-POS | B33: Catalogue trajets filtré par gare d'affectation agent (GET /routes?departure=user.gare) | C33: Agent | D33: Catalogue filtré | E33: Admin voit tout (pas de filtre), agent filtre departure. Grille responsive : 1 col <640px, 2 tablette, 3 ≥1280px. Trajets complets (0 place) grisés en bas. | F33: 0.75 | G33: 0.25 | H33: =F33+G33 -> 1
A34: UC-FE-POS | B34: Filtres catalogue : service commercial, code ligne (TCE/TA/MOR), recherche textuelle debounce 300ms | C34: Agent | D34: Filtres POS | E34: Dropdowns service (Tous / Train voyageur / Micheline Viko Viko / Trans Lémurie Express) et ligne, input debounce, compteur résultats visibles | F34: 0.5 | G34: 0.25 | H34: =F34+G34 -> 0.75
A35: UC-FE-POS | B35: Carte trajet : badge statut Disponible ≥10 (vert) / Stock faible 1–9 (orange) / Complet 0 (rouge + désactivé) | C35: Agent | D35: TrainCard | E35: Badge coloré mis à jour par SSE, serviceName + trainNumber, départ→arrivée, horaires, durée, operatingDays, classe, prix Ar | F35: 0.5 | G35: 0.25 | H35: =F35+G35 -> 0.75
A36: UC-FE-POS | B36: Formulaire passager : Nom, Prénom, CIN (obligatoires) + date de voyage (min = aujourd'hui) | C36: Agent | D36: Saisie passager | E36: Champs requis avec erreurs inline, date picker min=today, réinitialisation après "Ajouter au panier", validation avant ajout | F36: 0.25 | G36: 0.25 | H36: =F36+G36 -> 0.5
A37: UC-FE-POS | B37: Gestion du panier : ajout trajet, quantités +/−, suppression individuelle, sous-total par ligne | C37: Agent | D37: Panier | E37: Contrôle stock niveau 1 à l'ajout (qtyAlready + 1 > seatsAvailable), boutons +/- désactivés si stock insuffisant, suppression à quantité 0 | F37: 0.5 | G37: 0.5 | H37: =F37+G37 -> 1
A38: UC-FE-POS | B38: Calcul financier : Sous-total HT + TVA 20 % + Total TTC, formatage Ariary | C38: Agent | D38: Calcul TVA | E38: Σ(prix × qté), TVA = subtotal × 0.20, TTC = subtotal + tax, formatAriary() sur chaque montant, mise à jour réactive | F38: 0 | G38: 0.25 | H38: =F38+G38 -> 0.25
A39: UC-FE-POS | B39: Sélection opérateur Mobile Money (MVola / Orange Money / Airtel Money) avec bottom-sheet mobile | C39: Agent | D39: Paiement MM | E39: Boutons radio stylisés, sélection obligatoire avant validation, bottom-sheet sur mobile <640px, inline sur desktop | F39: 0.25 | G39: 0 | H39: =F39+G39 -> 0.25
A40: UC-FE-POS | B40: Validation + appel POST /sales + confirmation (toast/modal récapitulatif) | C40: Agent | D40: Finalisation vente | E40: Appel POST /sales avec les items du panier, gestion erreur 409 (stock insuffisant), toast succès avec ID vente, vidage panier | F40: 0 | G40: 0.5 | H40: =F40+G40 -> 0.5
A41: UC-FE-POS | B41: Mode lecture seule contrôleur (consultation catalogue sans panier ni actions de vente) | C41: Contrôleur | D41: Read-only POS | E41: Guard contrôleur masque panier, formulaire passager, boutons "Ajouter". Badge "Mode consultation uniquement". | F41: 0.25 | G41: 0.25 | H41: =F41+G41 -> 0.5
A42: Sous-total Module FE-5 — POS — Vente de billets | F42: =SUM(F33:F41) -> 3 | G42: =SUM(G33:G41) -> 2.5 | H42: =SUM(H33:H41) -> 5.5
A43: Module FE-6 — Réservation avec plan des sièges
A44: UC-FE-RES | B44: Flow réservation 4 étapes avec stepper : Trajet → Passager & Date → Siège → Paiement | C44: Agent | D44: Stepper réservation | E44: Indicateur visuel étapes (complété/actif/en attente), navigation prev/next, validation complète par étape, récapitulatif latéral persistant | F44: 0.5 | G44: 0.25 | H44: =F44+G44 -> 0.75
A45: UC-FE-RES | B45: Composant SeatMap headless : grille CSS 2+2 (A/B | allée | C/D), états libre/réservé/sélectionné | C45: Agent | D45: Composant SeatMap | E45: grid-cols-[1.5rem_1fr_1fr_0.75rem_1fr_1fr], n° rangée, légende états (fond clair/coloré/surligné), scroll horizontal mobile | F45: 0.75 | G45: 0.25 | H45: =F45+G45 -> 1
A46: UC-FE-RES | B46: buildSeatGrid() : 3 configurations (88/52/20 places), états depuis GET /reservations?routeId=&date= | C46: Agent | D46: Logique sièges | E46: SeatMapConfig[] pour Train voyageur (22 rangées), TLE (13), Micheline (5). Numérotation 1A–1D. Status free/reserved depuis réponse API. | F46: 0 | G46: 0.5 | H46: =F46+G46 -> 0.5
A47: UC-FE-RES | B47: Confirmation paiement → POST /reservations, gestion erreur 409 (conflit siège) + réouverture SeatMap | C47: Agent | D47: Appel API réservation | E47: Appel POST /reservations, si 409 → alerte "Siège déjà réservé" + réinitialisation étape siège, si 200 → modale confirmation avec numéro réservation | F47: 0 | G47: 0.5 | H47: =F47+G47 -> 0.5
A48: Sous-total Module FE-6 — Réservation avec plan des sièges | F48: =SUM(F44:F47) -> 1.25 | G48: =SUM(G44:G47) -> 1.5 | H48: =SUM(H44:H47) -> 2.75
A49: Module FE-7 — Réattribution de siège (passager absent)
A50: UC-FE-REASSIGN | B50: Liste des réservations du trajet avec badges statuts (confirmé / non présenté / réattribué) | C50: Agent | D50: Vue réservations | E50: GET /reservations?routeId=&date=, tableau filtré par trainNumber+date, badges colorés : vert/orange/gris | F50: 0.25 | G50: 0.25 | H50: =F50+G50 -> 0.5
A51: UC-FE-REASSIGN | B51: Action "Non présenté" → PATCH /reservations/:id/no-show + libération siège dans SeatMap | C51: Agent | D51: Marquage no-show | E51: Appel PATCH /:id/no-show, invalidation cache réservations, siège repasse à libre dans buildSeatGrid côté frontend | F51: 0 | G51: 0.25 | H51: =F51+G51 -> 0.25
A52: UC-FE-REASSIGN | B52: Formulaire réattribution + SeatMap → PATCH /reservations/:id/reassign | C52: Agent | D52: Réattribution | E52: Modal CIN/nom/prénom nouveau passager + SeatMap avec siège no_show libre, appel PATCH /:id/reassign, confirmation | F52: 0.25 | G52: 0.25 | H52: =F52+G52 -> 0.5
A53: Sous-total Module FE-7 — Réattribution de siège | F53: =SUM(F50:F52) -> 0.5 | G53: =SUM(G50:G52) -> 0.75 | H53: =SUM(H50:H52) -> 1.25
A54: Module FE-8 — Gestion des trajets
A55: UC-FE-ROUTES | B55: Tableau trajets (10 colonnes spec) avec code couleur places : vert ≥30 / jaune 10–29 / rouge <10 / gris = 0 | C55: Admin / Agent | D55: Liste trajets | E55: GET /routes, DataTable triable, colonnes : service, N° train, départ→arrivée, ligne, classe, départ, arrivée, durée, jours, prix Ar, places. Code couleur. | F55: 0.5 | G55: 0.25 | H55: =F55+G55 -> 0.75
A56: UC-FE-ROUTES | B56: Barre de recherche multicritères (gare de départ/arrivée, service, code ligne) | C56: Admin / Agent | D56: Filtres trajets | E56: Input live search, filtre combiné sur departure, arrival, serviceName, category, trainNumber — case insensitive | F56: 0.25 | G56: 0.25 | H56: =F56+G56 -> 0.5
A57: UC-FE-ROUTES | B57: Formulaire création/modification trajet (12 champs dont 10 obligatoires) → POST / PATCH /routes | C57: Admin | D57: CRUD trajet | E57: Tous champs spec §8.2, validation requis, heure HH:MM, prix positif, appel POST/PATCH, modal avec fermeture et refresh liste | F57: 0.5 | G57: 0.25 | H57: =F57+G57 -> 0.75
A58: UC-FE-ROUTES | B58: Suppression avec modale de confirmation → DELETE /routes/:id | C58: Admin | D58: Suppression trajet | E58: Confirmation "Trajet supprimé définitivement", appel DELETE, refresh liste, affichage confirmation visuelle | F58: 0 | G58: 0.25 | H58: =F58+G58 -> 0.25
A59: Sous-total Module FE-8 — Gestion des trajets | F59: =SUM(F55:F58) -> 1.25 | G59: =SUM(G55:G58) -> 1 | H59: =SUM(H55:H58) -> 2.25
A60: Module FE-9 — Historique des ventes
A61: UC-FE-SALES | B61: En-tête statistiques globales : total TTC cumulé, nb transactions, panier moyen, TVA collectée | C61: Tous | D61: KPIs historique | E61: GET /sales (toutes périodes), 4 cards métriques, formatAriary sur chaque valeur | F61: 0.25 | G61: 0.25 | H61: =F61+G61 -> 0.5
A62: UC-FE-SALES | B62: Tableau transactions : ID, Date & Heure, Agent, Gare, Nb billets, Total TTC, Opérateur, Action | C62: Tous | D62: Tableau ventes | E62: 8 colonnes, tri par date décroissant, pagination 20/page, responsive (colonnes masquées mobile) | F62: 0.5 | G62: 0.25 | H62: =F62+G62 -> 0.75
A63: UC-FE-SALES | B63: Modal détail vente : métadonnées + liste billets (trajet, classe, passager, CIN, siège) + récapitulatif TVA | C63: Tous | D63: Détail vente | E63: GET /sales/:id, en-tête date/agent/gare/opérateur, tableau SaleItem[] avec prix×qté, pied sous-total+TVA+TTC | F63: 0.25 | G63: 0.25 | H63: =F63+G63 -> 0.5
A64: UC-FE-SALES | B64: Export CSV "billets-madarail-YYYY-MM-DD.csv" (séparateur ; , 9 colonnes spec §9.4) | C64: Tous | D64: Export CSV | E64: Blob CSV, URL.createObjectURL, nom fichier date du jour, colonnes : ID;Date;Agent;Gare;Nb billets;Sous-total;TVA;Total;Opérateur | F64: 0 | G64: 0.25 | H64: =F64+G64 -> 0.25
A65: Sous-total Module FE-9 — Historique des ventes | F65: =SUM(F61:F64) -> 1 | G65: =SUM(G61:G64) -> 1 | H65: =SUM(H61:H64) -> 2
A66: Module FE-10 — Gestion des utilisateurs (admin)
A67: UC-FE-USERS | B67: Liste utilisateurs + stats (total/admins/agents/contrôleurs) + badges rôles colorés | C67: Admin | D67: Liste utilisateurs | E67: GET /users, compteurs en en-tête, tableau avec badges rôles (bleu/rouge/ambre), point d'exploitation, date création | F67: 0.5 | G67: 0.25 | H67: =F67+G67 -> 0.75
A68: UC-FE-USERS | B68: Formulaire création/modification : nom, email, mot de passe, rôle, point d'exploitation → POST/PATCH /users | C68: Admin | D68: CRUD utilisateurs | E68: Select rôle (Admin/Agent/Contrôleur), select gare depuis DEPARTURE_CITIES[], email unique, champ mdp masqué (création uniquement) | F68: 0.25 | G68: 0.25 | H68: =F68+G68 -> 0.5
A69: UC-FE-USERS | B69: Suppression avec confirmation → DELETE /users/:id (interdiction auto-suppression) | C69: Admin | D69: Suppression utilisateur | E69: Modale confirmation, guard anti-auto-suppression côté frontend, appel DELETE, refresh liste | F69: 0 | G69: 0.25 | H69: =F69+G69 -> 0.25
A70: Sous-total Module FE-10 — Gestion des utilisateurs | F70: =SUM(F67:F69) -> 0.75 | G70: =SUM(G67:G69) -> 0.75 | H70: =SUM(H67:H69) -> 1.5
A71: Module FE-11 — Synchronisation Bluetooth (simulation)
A72: UC-FE-BT | B72: Interface états BT : idle → scanning → connecting → transferring → done / error avec animations | C72: Agent / Contrôleur | D72: UI Bluetooth | E72: Progression animée (spinner, barre), icône Bluetooth Lucide, logs séquentiels en temps réel, gestion état error avec retry | F72: 0.5 | G72: 0.25 | H72: =F72+G72 -> 0.75
A73: UC-FE-BT | B73: Simulation transfert données (ventes + réservations en attente) via setTimeout séquentiels | C73: Agent / Contrôleur | D73: Simulation sync | E73: Compteurs nb ventes + nb réservations, simulation 4 étapes avec délais réalistes, récapitulatif "X ventes / Y réservations transférées" | F73: 0 | G73: 0.25 | H73: =F73+G73 -> 0.25
A74: Sous-total Module FE-11 — Synchronisation Bluetooth | F74: =SUM(F72:F73) -> 0.5 | G74: =SUM(G72:G73) -> 0.5 | H74: =SUM(H72:H73) -> 1
A75: Module FE-12 — Mode hors-ligne & PWA
A76: UC-FE-PWA | B76: Service Worker Workbox + manifest PWA (thème madarail) + icônes + mode standalone installable | C76: Développeur | D76: PWA core | E76: vite-plugin-pwa, workbox-window, manifest.json avec name/theme_color navy, icônes 192+512px, installable Android/iOS/Chrome | F76: 0 | G76: 0.5 | H76: =F76+G76 -> 0.5
A77: UC-FE-PWA | B77: Stratégie cache : seed trajets + profil utilisateur à la connexion (IndexedDB), TTL 24h | C77: Développeur | D77: Cache données | E77: Appel GET /routes + GET /auth/me au login, stockage IndexedDB, TTL 24h, invalidation à la reconnexion si TTL expiré | F77: 0 | G77: 0.75 | H77: =F77+G77 -> 0.75
A78: UC-FE-PWA | B78: File d'attente ventes hors-ligne (IndexedDB) + synchronisation automatique au retour en ligne | C78: Développeur | D78: Queue sync offline | E78: IndexedDB store "pending-sales", écriture systématique si !isOnline, listener window.online → POST /sales en batch, gestion erreurs, badge compteur en attente | F78: 0 | G78: 1 | H78: =F78+G78 -> 1
A79: Sous-total Module FE-12 — Mode hors-ligne & PWA | F79: =SUM(F76:F78) -> 0 | G79: =SUM(G76:G78) -> 2.25 | H79: =SUM(H76:H78) -> 2.25
A80: Module FE-13 — Tests frontend & Qualité
A81: UC-FE-QA | B81: Tests unitaires Vitest : calcul TVA, contrôle stock, formatAriary, buildSeatGrid (~15 cas) | C81: Développeur | D81: Tests unitaires | E81: Vitest, fonctions pures : formatAriary, calcul subtotal/tax/total, contrôle stock niveau 1, buildSeatGrid états pour les 3 configs | F81: 0 | G81: 0.5 | H81: =F81+G81 -> 0.5
A82: UC-FE-QA | B82: Tests composants React Testing Library : POS (ajout panier), SeatMap (sélection siège), form passager | C82: Développeur | D82: Tests composants | E82: RTL + user-event, mock axios, interactions : ajout billet au panier, sélection siège disponible/occupé, soumission formulaire invalide | F82: 0 | G82: 0.5 | H82: =F82+G82 -> 0.5
A83: UC-FE-QA | B83: Audit responsive (375px / 768px / 1280px) + accessibilité axe-core + Lighthouse ≥ 85 | C83: Développeur | D83: QA & audit | E83: Chrome DevTools responsive, axe-core aria-labels/contrastes/focus, Lighthouse perf+a11y, corrections ciblées | F83: 0.25 | G83: 0 | H83: =F83+G83 -> 0.25
A84: Sous-total Module FE-13 — Tests frontend | F84: =SUM(F81:F83) -> 0.25 | G84: =SUM(G81:G83) -> 1 | H84: =SUM(H81:H83) -> 1.25
A85: ━━━ SECTION B — BACKEND (NestJS · PostgreSQL 16 · Prisma · JWT · SSE · Docker) ━━━
A86: Module BE-0 — Setup NestJS + Prisma + Docker
A87: UC-BE-SETUP | B87: Init NestJS (CLI, ConfigModule, ValidationPipe globale, CORS, Helmet, logger Pino) | C87: Développeur | D87: Bootstrap NestJS | E87: @nestjs/config avec validation Joi, class-validator + class-transformer globaux, cors origin VITE_APP_URL, pino-http logger structuré | F87: 0 | G87: 0 | H87: =F87+G87 -> 0
A88: UC-BE-SETUP | B88: Schéma Prisma : 6 models (User, Route, Sale, SaleItem, Reservation, ReassignedTo) + enums Role/ReservationStatus | C88: Développeur | D88: Schéma Prisma | E88: Models avec relations, clés étrangères, index (departure, createdAt, routeId+travelDate), enums ADMIN/AGENT/CONTROLLER et CONFIRMED/NO_SHOW/REASSIGNED | F88: 0 | G88: 1 | H88: =F88+G88 -> 1
A89: UC-BE-SETUP | B89: Migrations Prisma + seed initial (trajets de référence Madarail + compte admin) | C89: Développeur | D89: Migrations & seed | E89: prisma migrate dev, fichier seed.ts avec 10 trajets de référence (lignes TCE/TA/MOR), 1 admin, 3 agents, 1 contrôleur | F89: 0 | G89: 0.5 | H89: =F89+G89 -> 0.5
A90: UC-BE-SETUP | B90: Docker Compose : postgres:16-alpine + api NestJS + nginx (frontend build multi-stage) | C90: Développeur | D90: Docker Compose | E90: Service db avec healthcheck, api depends_on:db, Dockerfile multi-stage (builder node:20-alpine → production node:20-alpine slim), web nginx:alpine avec config proxy /api → api:3000 | F90: 0 | G90: 0.75 | H90: =F90+G90 -> 0.75
A91: UC-BE-SETUP | B91: .env.example complet + Makefile (make dev, make build, make migrate, make seed) | C91: Développeur | D91: Config & outillage | E91: Variables : DATABASE_URL, JWT_SECRET, JWT_REFRESH_SECRET, JWT_EXPIRES, JWT_REFRESH_EXPIRES, CORS_ORIGIN. Makefile pour réduire les commandes Docker/Prisma fréquentes. | F91: 0 | G91: 0.5 | H91: =F91+G91 -> 0.5
A92: Sous-total Module BE-0 — Setup NestJS + Prisma + Docker | F92: =SUM(F87:F91) -> 0 | G92: =SUM(G87:G91) -> 2.75 | H92: =SUM(H87:H91) -> 2.75
A93: Module BE-1 — Authentification JWT (login, refresh, logout, guards)
A94: UC-BE-AUTH | B94: Module Auth NestJS + Passport : JwtStrategy (access 15min) + JwtRefreshStrategy (refresh 7j httpOnly cookie) | C94: Développeur | D94: Auth module | E94: @nestjs/passport, @nestjs/jwt, JwtStrategy valide Bearer header, JwtRefreshStrategy lit cookie "refresh_token" httpOnly Secure SameSite=Strict | F94: 0 | G94: 0.75 | H94: =F94+G94 -> 0.75
A95: UC-BE-AUTH | B95: POST /auth/login : validation credentials, génération paire tokens, cookie refresh httpOnly | C95: Développeur | D95: Login endpoint | E95: bcrypt.compare, génération access JWT + refresh JWT, Set-Cookie refresh_token httpOnly, retour { accessToken, user: {id, email, name, role, gare} } | F95: 0 | G95: 0.75 | H95: =F95+G95 -> 0.75
A96: UC-BE-AUTH | B96: POST /auth/refresh : validation refresh token (cookie), rotation token, nouveau access token | C96: Développeur | D96: Refresh endpoint | E96: Lecture cookie, vérification JWT, rotation (nouveau refresh émis, ancien révoqué en DB ou champ revokedAt), retour nouvel accessToken | F96: 0 | G96: 0.75 | H96: =F96+G96 -> 0.75
A97: UC-BE-AUTH | B97: POST /auth/logout : révocation refresh token + suppression cookie | C97: Développeur | D97: Logout endpoint | E97: Invalidation refresh token (champ revokedAt ou suppression), Set-Cookie refresh_token="" Max-Age=0 | F97: 0 | G97: 0.25 | H97: =F97+G97 -> 0.25
A98: UC-BE-AUTH | B98: JwtAuthGuard (global sauf routes publiques) + RolesGuard + décorateur @Roles() | C98: Développeur | D98: Guards & décorateurs | E98: JwtAuthGuard appliqué globalement via APP_GUARD, @Public() pour /auth/*, RolesGuard vérifie req.user.role vs @Roles(Role.ADMIN), décorateur @CurrentUser() | F98: 0 | G98: 0.5 | H98: =F98+G98 -> 0.5
A99: Sous-total Module BE-1 — Authentification JWT | F99: =SUM(F94:F98) -> 0 | G99: =SUM(G94:G98) -> 3 | H99: =SUM(H94:H98) -> 3
A100: Module BE-2 — API Trajets (CRUD)
...

Sheet Charges Complémentaires
A1: CHARGES COMPLÉMENTAIRES — MAÎTRISE D'ŒUVRE
A2: Ratios appliqués sur le total développement. Modifier le TJM (cellule jaune) pour recalculer.
A3: Poste MOE | B3: Profil | C3: TJM (€) | D3: Ratio (base 1 = codage) | G3: Total charges (j/h)
A4: Direction de projet | B4: Chef de projet | C4: =$B15 -> 100 | D4: 0.03 | G4: =D4*Backlog!H138 -> 1.3575
A5: Recette fonctionnelle | B5: Chef de projet | C5: =$B15 -> 100 | D5: 0.07 | G5: =D5*Backlog!H138 -> 3.1675
A6: Plan de test & cas de test | B6: Anal. fonctionnel | C6: =$B15 -> 100 | D6: 0.03 | G6: =D6*Backlog!H138 -> 1.3575
A7: Rédaction doc technique/API | B7: Tech Lead | C7: =$B15 -> 100 | D7: 0.02 | G7: =D7*Backlog!H138 -> 0.905
A8: Coordination technique | B8: Tech Lead | C8: =$B15 -> 100 | D8: 0.03 | G8: =D8*Backlog!H138 -> 1.3575
A9: Code review & qualité | B9: Tech Lead | C9: =$B15 -> 100 | D9: 0.0217 | G9: =D9*Backlog!H138 -> 0.981925
A10: Déploiements Docker & MEP | B10: DevOps | C10: =$B15 -> 100 | D10: 0.03 | G10: =D10*Backlog!H138 -> 1.3575
A11: Total ratios MOE | D11: =SUM(D4:D10) -> 0.2317 | G11: =SUM(G4:G10) -> 10.484425
A12: Total général (j/h — codage + MOE) | G12: =Backlog!H138+G11 -> 55.734425
A14: BUDGET ESTIMATIF
A15: TJM moyen (€) | B15: 100 | C15: ← Modifier pour recalculer
A16: Total j/h chargés | B16: =G12 -> 55.734425
A17: Budget HT estimé | B17: =B16*B15 -> 5573.4425
A18: TVA 20 % | B18: =B17*0.2 -> 1114.6885
A19: Budget TTC estimé | B19: =B17+B18 -> 6688.131

Sheet Macro-Planning
A1: MACRO-PLANNING — MADARAIL POS (12 semaines · 2 devs senior + Claude Code AI)
A2: Phase / Tâche | B2: S1 | C2: S2 | D2: S3 | E2: S4 | F2: S5 | G2: S6 | H2: S7 | I2: S8 | J2: S9 | K2: S10 | L2: S11 | M2: S12
A3: Phase 1 — Socle technique (Frontend + Backend en parallèle) S1–S2
A4: Init NestJS + Prisma schéma + migrations + seed | B4: =REPT("█",5) -> █████
A5: Docker Compose (postgres + api + nginx) | B5: =REPT("█",5) -> █████
A6: Init React/Vite + Tailwind + AppContext + PWA setup | B6: =REPT("█",5) -> █████
A7: Auth JWT backend (login, refresh, logout, guards) | B7: =REPT("█",5) -> █████ | C7: =REPT("█",5) -> █████
A8: Auth frontend (page login, intercepteur Axios refresh, guards vues) | C8: =REPT("█",5) -> █████
A9: Layout Sidebar responsive + OfflineIndicator | C9: =REPT("█",5) -> █████
A10: Phase 2 — API Core + POS — Caisse billets S3–S5
A11: API Trajets (GET/POST/PATCH/DELETE) + DTOs + validation | D11: =REPT("█",5) -> █████
A12: Couche API client Axios (services + hooks + SSE hook) | D12: =REPT("█",5) -> █████
A13: Catalogue POS filtré + filtres service/ligne + TrainCard | D13: =REPT("█",5) -> █████ | E13: =REPT("█",5) -> █████
A14: API Ventes (transaction Prisma atomique + décrémentation stock) | E14: =REPT("█",5) -> █████
A15: Panier + formulaire passager + calcul TVA + sélection Mobile Money | E15: =REPT("█",5) -> █████ | F15: =REPT("█",5) -> █████
A16: Validation POST /sales + gestion erreur 409 + confirmation | F16: =REPT("█",5) -> █████
A17: Phase 3 — Réservation, SeatMap & Temps réel S5–S7
A18: API Réservations (SELECT FOR UPDATE, no-show, reassign) | F18: =REPT("█",5) -> █████ | G18: =REPT("█",5) -> █████
A19: SeatMap composant + buildSeatGrid 3 configs (88/52/20 places) | F19: =REPT("█",5) -> █████ | G19: =REPT("█",5) -> █████
A20: Flow réservation 4 étapes + POST /reservations + erreur 409 | G20: =REPT("█",5) -> █████
A21: SSE backend (EventEmitter2 + @Sse endpoint + heartbeat) | G21: =REPT("█",5) -> █████ | H21: =REPT("█",5) -> █████
A22: Réattribution siège (no-show → SeatMap → reassign) | H22: =REPT("█",5) -> █████
A23: Phase 4 — Dashboard, Historique & Administration S7–S9
A24: Tableau de bord (KPIs du jour, Top 5, barres Mobile Money, histogramme) | H24: =REPT("█",5) -> █████ | I24: =REPT("█",5) -> █████
A25: Historique des ventes (tableau, modal détail, export CSV) | I25: =REPT("█",5) -> █████
A26: API Utilisateurs (CRUD) + CRUD utilisateurs frontend | I26: =REPT("█",5) -> █████ | J26: =REPT("█",5) -> █████
A27: CRUD Trajets frontend (tableau, filtres, formulaire, suppression) | J27: =REPT("█",5) -> █████
A28: Bluetooth simulation (états animés, compteurs ventes/réservations) | J28: =REPT("█",5) -> █████
A29: Phase 5 — Mode hors-ligne, Tests & Documentation S9–S11
A30: PWA : SW Workbox + cache IndexedDB trajets + queue ventes offline | J30: =REPT("█",5) -> █████ | K30: =REPT("█",5) -> █████
A31: Tests E2E NestJS (Supertest : auth, transaction vente, anti-conflit) | K31: =REPT("█",5) -> █████
A32: Documentation Swagger/OpenAPI (@nestjs/swagger) | K32: =REPT("█",5) -> █████
A33: Tests unitaires Vitest + tests composants RTL (frontend) | K33: =REPT("█",5) -> █████ | L33: =REPT("█",5) -> █████
A34: Audit responsive (375/768/1280px) + accessibilité axe-core + Lighthouse | L34: =REPT("█",5) -> █████
A35: Phase 6 — Recette fonctionnelle & Mise en production S11–S12
A36: Recette fonctionnelle (scénarios POS, réservation, hors-ligne) | L36: =REPT("█",5) -> █████ | M36: =REPT("█",5) -> █████
A37: Corrections post-recette | M37: =REPT("█",5) -> █████
A38: Déploiement Docker production + configuration HTTPS (nginx + Certbot) | M38: =REPT("█",5) -> █████
A40: Capacité estimée : ~3 j/h par développeur par semaine | Frontend : Dev 1 (spécialiste React/TypeScript) | Backend : Dev 2 (spécialiste NestJS/PostgreSQL) | Phases 5 & 6 : convergence des deux devs
